pynfc/__init__.py
pynfc/freefare.py
pynfc/mifare.py
pynfc/nfc.py
pynfc-0.0.2.dist-info/DESCRIPTION.rst
pynfc-0.0.2.dist-info/METADATA
pynfc-0.0.2.dist-info/RECORD
pynfc-0.0.2.dist-info/WHEEL
pynfc-0.0.2.dist-info/metadata.json
pynfc-0.0.2.dist-info/top_level.txt
