Metadata-Version: 2.0
Name: pynfc
Version: 0.0.2
Summary: `ctypeslib` converted libnfc and libfreefare
Home-page: https://github.com/BarnabyShearer/pynfc.git
Author: Barnaby Shearer
Author-email: b@Zi.iS
License: BSD
Keywords: RFID NFC Mifare Desfire
Platform: UNKNOWN
Classifier: Development Status :: 4 - Beta
Classifier: Environment :: Web Environment
Classifier: License :: OSI Approved :: BSD License
Classifier: Programming Language :: Python :: 2
Classifier: Programming Language :: Python :: 3
Requires-Dist: psutil
